simple_money/__init__.py
simple_money-0.1.2.dist-info/DESCRIPTION.rst
simple_money-0.1.2.dist-info/METADATA
simple_money-0.1.2.dist-info/RECORD
simple_money-0.1.2.dist-info/WHEEL
simple_money-0.1.2.dist-info/metadata.json
simple_money-0.1.2.dist-info/top_level.txt
tests/__init__.py
tests/conftest.py
tests/test_base.py
tests/test_combo.py
