Metadata-Version: 2.0
Name: simple-money
Version: 0.1.2
Summary: A simple interface to work with money-related entities.
Home-page: https://github.com/Stranger6667/simple-money
Author: Dmitry Dygalo
Author-email: dadygalo@gmail.com
License: MIT
Keywords: money,finance
Platform: UNKNOWN
Classifier: Development Status :: 3 - Alpha
Classifier: Topic :: Office/Business :: Financial
Classifier: Topic :: Software Development :: Libraries :: Python Modules
Classifier: Intended Audience :: Developers
Classifier: Operating System :: OS Independent
Classifier: License :: OSI Approved :: MIT License
Classifier: Programming Language :: Python
Classifier: Programming Language :: Python :: 2.6
Classifier: Programming Language :: Python :: 2.7
Classifier: Programming Language :: Python :: 3.2
Classifier: Programming Language :: Python :: 3.3
Classifier: Programming Language :: Python :: 3.4
Classifier: Programming Language :: Python :: 3.5
Classifier: Programming Language :: Python :: Implementation :: CPython
Classifier: Programming Language :: Python :: Implementation :: PyPy
Classifier: Programming Language :: Python :: Implementation :: Jython
